gcloud_aio_run-1.0.0-py3.9-nspkg.pth
gcloud/aio/run/__init__.py
gcloud/aio/run/py.typed
gcloud/aio/run/run_client.py
gcloud/aio/run/run_service.py
gcloud_aio_run-1.0.0.dist-info/METADATA
gcloud_aio_run-1.0.0.dist-info/WHEEL
gcloud_aio_run-1.0.0.dist-info/namespace_packages.txt
gcloud_aio_run-1.0.0.dist-info/top_level.txt
gcloud_aio_run-1.0.0.dist-info/RECORD
