Metadata-Version: 2.1
Name: gcloud-aio-run
Version: 1.0.0
Summary: Python Client for Google Cloud Run
Home-page: https://github.com/cbuschka/gcloud-aio-run
Author: Cornelius Buschka
Author-email: cbuschka@gmail.com
License: Apache Software License
Platform: Posix; MacOS X; Windows
Classifier: Development Status :: 5 - Production/Stable
Classifier: Intended Audience :: Developers
Classifier: License :: OSI Approved :: Apache Software License
Classifier: Operating System :: OS Independent
Classifier: Programming Language :: Python :: 3
Classifier: Programming Language :: Python :: 3.6
Classifier: Programming Language :: Python :: 3.7
Classifier: Programming Language :: Python :: 3.8
Classifier: Programming Language :: Python :: 3.9
Classifier: Topic :: Internet
Requires-Python: >= 3.6
Requires-Dist: gcloud-aio-auth (<4.0.0,>=3.3.0)
